neolite/__init__.py
neolite-0.7.4.dist-info/LICENSE
neolite-0.7.4.dist-info/METADATA
neolite-0.7.4.dist-info/WHEEL
neolite-0.7.4.dist-info/top_level.txt
neolite-0.7.4.dist-info/RECORD
