Metadata-Version: 2.1
Name: neolite
Version: 0.7.4
Summary: Super light weight neo4j python driver with multi-graph support.
Home-page: https://github.com/John-Theo/neolite
Author: John Theo
Author-email: xinhaozhuang.work@gmail.com
License: UNKNOWN
Platform: UNKNOWN
Classifier: Programming Language :: Python :: 3
Classifier: License :: OSI Approved :: MIT License
Classifier: Operating System :: OS Independent
Requires-Python: >=3.6
Requires-Dist: requests
